starmap_client/__init__.py
starmap_client/client.py
starmap_client/models.py
starmap_client/session.py
starmap_client/utils.py
starmap_client/providers/__init__.py
starmap_client/providers/base.py
starmap_client/providers/memory.py
starmap_client/providers/utils.py
starmap_client-2.4.0.dist-info/LICENSE
starmap_client-2.4.0.dist-info/METADATA
starmap_client-2.4.0.dist-info/WHEEL
starmap_client-2.4.0.dist-info/top_level.txt
starmap_client-2.4.0.dist-info/RECORD
