Metadata-Version: 2.1
Name: starmap-client
Version: 2.4.0
Summary: Client for StArMap
Home-page: https://github.com/release-engineering/starmap-client
Author: Jonathan Gangi
Author-email: jgangi@redhat.com
License: GPLv3+
Keywords: stratosphere content artifact mapping cli
Classifier: License :: OSI Approved :: GNU General Public License v3 or later (GPLv3+)
Classifier: Programming Language :: Python :: 3.10
Classifier: Programming Language :: Python :: 3.11
Classifier: Programming Language :: Python :: 3.12
Classifier: Programming Language :: Python :: 3.13
License-File: LICENSE
Requires-Dist: attrs
Requires-Dist: requests
Requires-Dist: requests-mock
Requires-Dist: urllib3
